pygame_particles/__init__.py
pygame_particles/container.py
pygame_particles/examples.py
pygame_particles/particle.py
pygame_particles/shape.py
pygame_particles-1.1.dist-info/LICENSE
pygame_particles-1.1.dist-info/METADATA
pygame_particles-1.1.dist-info/WHEEL
pygame_particles-1.1.dist-info/top_level.txt
pygame_particles-1.1.dist-info/RECORD
