Metadata-Version: 2.1
Name: pygame-particles
Version: 1.1
Summary: A small example package
Author: Vitness
Project-URL: Homepage, https://github.com/VitnessYT/pygame-particles
Project-URL: Bug Tracker, https://github.com/VitnessYT/pygame-particles/issues
Classifier: Programming Language :: Python :: 3
Classifier: License :: OSI Approved :: MIT License
Classifier: Operating System :: OS Independent
Requires-Python: >=3.7
License-File: LICENSE
Requires-Dist: pygame
